rekover/__init__.py
rekover/main.py
rekover-0.0.1.dist-info/METADATA
rekover-0.0.1.dist-info/WHEEL
rekover-0.0.1.dist-info/top_level.txt
rekover-0.0.1.dist-info/RECORD
