Metadata-Version: 2.1
Name: rekover
Version: 0.0.1
Summary: rekover project
Home-page: https://github.com/yourusername/my_package
Author: Francisco Costa
Author-email: francisco@rekover.ai
Classifier: Programming Language :: Python :: 3
Classifier: License :: OSI Approved :: MIT License
Classifier: Operating System :: OS Independent
Requires-Python: >=3.6
